Workbook

Sheet Cases
A1: TC ID | B1: Module | C1: Submodule | D1: Role | E1: Scope | F1: Priority | G1: Precondition | H1: Steps | I1: Expected Result | J1: Actual Result | K1: Status | L1: Screenshot Required | M1: Screenshot File | N1: Bug ID | O1: Tester | P1: Date | Q1: Notes
A2: TC-AUTH-001 | B2: AUTH | C2: Login | D2: Employee | E2: own | F2: Critical | G2: Active employee account; first-login flag off. | H2: 1. Open /login in a private window. 2. Enter the registered email and correct password. 3. Press Sign in. 4. Note the landing page and the sidebar items. | I2: Login succeeds, lands on the employee dashboard "/", sidebar shows only employee items (Dashboard, My Profile, Attendance, Leave, Holidays, Work From Home, Overtime, Documents, Inbox, Help & Guide and similar). No HR/Finance/Admin item appears. | K2: NOT TESTED | L2: YES | M2: EMP-AUTH-TC-AUTH-001-employee-landing.png | Q2: URL: /login
A3: TC-AUTH-002 | B3: AUTH | C3: Login | D3: HR Admin | E3: all | F3: Critical | G3: Active HR Admin account. | H3: 1. Sign in as HR Admin. 2. Note the landing page. | I3: HR Admin reaches the dashboard permitted for the role (HR dashboard /dashboard/hr-admin or "/"). No error page. | K3: NOT TESTED | L3: YES | M3: HR-AUTH-TC-AUTH-002-hr-landing.png | Q3: URL: /login
A4: TC-AUTH-003 | B4: AUTH | C4: Login | D4: Finance | E4: finance | F4: Critical | G4: Active Finance account. | H4: 1. Sign in as Finance. 2. Note landing page and sidebar. | I4: Finance lands on its dashboard; Payroll group is visible; Employees management, Settings and Performance admin items are not. | K4: NOT TESTED | L4: YES | M4: FIN-AUTH-TC-AUTH-003-finance-landing.png | Q4: URL: /login
A5: TC-AUTH-004 | B5: AUTH | C5: Login | D5: Director / Department Head | E5: department | F5: Critical | G5: Active Department Head assigned to Sales. | H5: 1. Sign in as the Sales Department Head. 2. Note landing page and sidebar. | I5: Lands on the department view; every list and card shows Sales employees only (D1). | K5: NOT TESTED | L5: YES | M5: DIR-AUTH-TC-AUTH-004-dept-head-landing.png | Q5: URL: /login
A6: TC-AUTH-005 | B6: AUTH | C6: Login failure | D6: Employee | E6: own | F6: Critical | G6: Active employee account. | H6: 1. Enter the correct email and a wrong password; submit. 2. Enter a malformed email such as "abc@"; submit. 3. Enter an unregistered email with any password; submit. | I6: Each attempt is refused with a generic error. The message does not reveal whether the email exists. No stack trace. Field error is shown beside the email/password field. | K6: NOT TESTED | L6: YES | M6: EMP-AUTH-TC-AUTH-005-invalid-credentials.png | Q6: URL: /login
A7: TC-AUTH-006 | B7: AUTH | C7: Login throttle | D7: Employee | E7: own | F7: High | G7: Active employee account. | H7: 1. Submit a wrong password 6 times within one minute. 2. Then submit the correct password immediately. | I7: After repeated failures the form shows a "too many attempts / try again in N seconds" message and refuses even the correct password until the wait ends (limit is 5 per minute). | K7: NOT TESTED | L7: YES | M7: EMP-AUTH-TC-AUTH-006-throttle.png | Q7: URL: /login
A8: TC-AUTH-007 | B8: AUTH | C8: Inactive / resigned | D8: Employee | E8: own | F8: Critical | G8: Staging test employee with status Inactive; another whose last working day was yesterday (exit record). | H8: 1. Sign in as the inactive employee. 2. Sign in as the employee whose last working day has passed. 3. If any session was already open for either, refresh an authenticated page. | I8: Neither account can use the application: sign-in is refused or the user is signed out immediately. No data page loads. | K8: NOT TESTED | L8: YES | M8: EMP-AUTH-TC-AUTH-007-inactive-blocked.png | Q8: URL: /login
A9: TC-AUTH-008 | B9: AUTH | C9: Resigned without exit record | D9: HR Admin | E9: all | F9: High | G9: Staging employee set to status Resigned (or Terminated) with NO exit record. | H9: 1. Set the status as stated on staging only. 2. Sign in as that employee. | I9: Record the result. Expected per spec: access is revoked. Known gap EMP-34: such users may still sign in. Mark FAIL if access is still granted and link EMP-34. | K9: NOT TESTED | L9: YES | M9: HR-AUTH-TC-AUTH-008-resigned-no-exit.png | Q9: Gap EMP-34 | URL: /login
A10: TC-AUTH-009 | B10: AUTH | C10: Logout | D10: Employee | E10: own | F10: High | G10: Signed in. | H10: 1. Open the user menu and choose Log out. 2. Press the browser Back button. 3. Paste a previously visited authenticated URL, e.g. /attendance/my. | I10: Session ends; Back and the pasted URL redirect to /login. No cached private page content is shown. | K10: NOT TESTED | L10: YES | M10: EMP-AUTH-TC-AUTH-009-logout.png | Q10: URL: /
A11: TC-AUTH-010 | B11: AUTH | C11: Session expiry | D11: Employee | E11: own | F11: Medium | G11: Signed in; session lifetime known from environment (default 480 min). | H11: 1. Leave the session idle past the configured lifetime (on staging, ask the admin to shorten it for the test). 2. Click any sidebar item. | I11: User is sent to /login. After signing in again the original request is not replayed unsafely. | K11: NOT TESTED | L11: NO | Q11: URL: /attendance/my
A12: TC-AUTH-011 | B12: AUTH | C12: Password change | D12: Employee | E12: own | F12: High | G12: Signed in employee. | H12: 1. Open the password settings. 2. Enter the wrong current password; submit. 3. Enter the right current password and a weak new password (e.g. "abc123"); submit. 4. Enter a compliant new password (12+ chars, mixed case, number, symbol); submit. 5. Log out and sign in with the new password. | I12: Wrong current password and weak password are refused with errors beside the correct fields. The compliant password is accepted; the old password stops working. | K12: NOT TESTED | L12: YES | M12: EMP-AUTH-TC-AUTH-011-password-change.png | Q12: URL: /settings/password (Profile > Password)
A13: TC-AUTH-012 | B13: AUTH | C13: First-login password | D13: Employee | E13: own | F13: High | G13: Newly invited employee with the forced-change flag. | H13: 1. Sign in with the temporary password. 2. Try to open /attendance/my directly. 3. Complete the forced change at /set-password. | I13: User is held on the set-password page until a compliant password is saved; other pages redirect there. After saving, normal navigation works. | K13: NOT TESTED | L13: YES | M13: EMP-AUTH-TC-AUTH-012-first-login.png | Q13: URL: /login
A14: TC-AUTH-013 | B14: AUTH | C14: Password reset | D14: Employee | E14: own | F14: High | G14: Mail sink (log/mailpit) available on staging. | H14: 1. Request a reset for a real employee email. 2. Request one for an unregistered email. 3. Open the reset link from the mail sink and set a compliant password. 4. Reuse the same link a second time. | I14: Both requests show the same neutral confirmation. The link works once; reuse is refused. Sign-in works with the new password. | K14: NOT TESTED | L14: YES | M14: EMP-AUTH-TC-AUTH-013-password-reset.png | Q14: URL: /forgot-password
A15: TC-AUTH-014 | B15: AUTH | C15: Role change | D15: HR Admin | E15: all | F15: Critical | G15: Two browsers; a staging employee who can be promoted to Manager and back. | H15: 1. Browser A: sign in as the employee; open /time-off/team (expect 403). 2. Browser B: as HR/SA grant the Manager role. 3. Browser A: reload /time-off/team. 4. Browser B: revoke the role. 5. Browser A: reload /time-off/team again. | I15: Step 1 403; after grant the page opens (team only); after revoke it returns to 403 on the next request. Menu and URL always agree. | K15: NOT TESTED | L15: YES | M15: HR-AUTH-TC-AUTH-014-role-change.png | Q15: URL: /settings/roles
A16: TC-AUTH-015 | B16: AUTH | C16: Disabled account | D16: Super Admin | E16: all | F16: Critical | G16: Staging account that is signed in elsewhere. | H16: 1. As SA deactivate the signed-in test employee (lifecycle status to Inactive with a past last working day). 2. In the other browser click any link. | I16: The deactivated user cannot continue; they are signed out or blocked on the next request. | K16: NOT TESTED | L16: YES | M16: SA-AUTH-TC-AUTH-015-disabled-account.png | Q16: URL: /employees
A17: TC-RBAC-001 | B17: RBAC | C17: Director scope | D17: Director / Department Head | E17: department | F17: Critical | G17: Sales Department Head; Sales employee S1 and Marketing employee K1 exist. | H17: 1. Open /employees. 2. Search for K1 (Marketing). 3. Open /employees/{K1 id}/profile and /employees/{K1 id}/edit by typing the URL. 4. Open /attendance/employees and filter by K1. | I17: List and search show Sales only. K1 profile/edit URLs give 403 or an authorised-denial page. K1 never appears in attendance. No Marketing name, salary or leave is leaked in any message. | K17: NOT TESTED | L17: YES | M17: DIR-RBAC-TC-RBAC-001-dept-isolation.png | Q17: D1 | URL: /employees
A18: TC-RBAC-002 | B18: RBAC | C18: Director no company-wide edit | D18: Director / Department Head | E18: department | F18: Critical | G18: Department Head with default scope only. | H18: 1. Open /employees/create. 2. If it opens, try to create an employee in Marketing. 3. Open /employees/{Sales id}/offboarding and /employees/{Sales id}/edit. | I18: Per D1 a Director has no company-wide employee edit, offboarding or salary access unless explicitly granted. Record exactly what opens. Any company-wide create/edit/offboard is a FAIL. | K18: NOT TESTED | L18: YES | M18: DIR-RBAC-TC-RBAC-002-director-no-crud.png | Q18: D1; gap EMP-15/44 | URL: /employees/create
A19: TC-RBAC-003 | B19: RBAC | C19: Director salary | D19: Director / Department Head | E19: department | F19: Critical | G19: Department Head; Sales employee S1. | H19: 1. Open /employees/{S1 id}/finance-profile. 2. Open /dashboard/finance. 3. Open /payroll/finance-approve and /payroll/process. | I19: All four are denied (403) unless the Director was explicitly granted payroll permission in Roles & Permissions. No salary figure is shown. | K19: NOT TESTED | L19: YES | M19: DIR-RBAC-TC-RBAC-003-director-salary-denied.png | Q19: D1; RBAC-28/PAY-75 | URL: /employees/{S1}/finance-profile
A20: TC-RBAC-004 | B20: RBAC | C20: Manager team scope | D20: Manager | E20: team | F20: Critical | G20: Sales Manager with two direct reports; another Sales employee not reporting to them. | H20: 1. Open /time-off/team. 2. Open /attendance/team. 3. Search for the non-report Sales employee. | I20: Only the two direct reports appear. The non-report is absent from lists and from search. | K20: NOT TESTED | L20: YES | M20: MGR-RBAC-TC-RBAC-004-team-isolation.png | Q20: URL: /time-off/team
A21: TC-RBAC-005 | B21: RBAC | C21: Manager forbidden URLs | D21: Manager | E21: team | F21: Critical | G21: Signed in as Sales Manager. | H21: 1. Type each URL: /employees/create, /settings/roles, /payroll/process, /dashboard/hr-admin, /dashboard/finance, /settings/audit-log, /overtime/windows. | I21: Each returns 403 (or redirects to an allowed page). None shows data or a form. | K21: NOT TESTED | L21: YES | M21: MGR-RBAC-TC-RBAC-005-manager-forbidden.png | Q21: URL: /employees/create
A22: TC-RBAC-006 | B22: RBAC | C22: Employee forbidden URLs | D22: Employee | E22: own | F22: Critical | G22: Signed in as employee. | H22: 1. Type each URL: /time-off/team, /attendance/team, /attendance/employees, /employees/create, /payroll/process, /payroll/overview, /settings/roles, /reports/attendance-summary.csv, /dashboard/manager. | I22: Each returns 403. Nothing downloads. | K22: NOT TESTED | L22: YES | M22: EMP-RBAC-TC-RBAC-006-employee-forbidden.png | Q22: URL: /time-off/team
A23: TC-RBAC-007 | B23: RBAC | C23: Finance forbidden URLs | D23: Finance | E23: finance | F23: Critical | G23: Signed in as Finance. | H23: 1. Type each URL: /settings/roles, /employees/create, /employees/{id}/edit, /attendance/settings, /performance/cycles, /dashboard/hr-admin. | I23: Each returns 403. Finance never edits employees or settings. | K23: NOT TESTED | L23: YES | M23: FIN-RBAC-TC-RBAC-007-finance-forbidden.png | Q23: URL: /settings/roles
... A213: TC-ERR-005 | B213: ERR | C213: 500 safe page | D213: Super Admin | E213: all | F213: Medium | G213: Staging with debug OFF. | H213: 1. With APP_DEBUG=false trigger a harmless error if a test hook exists (ask developer) or review any 500 found during testing. | I213: Generic error page; no SQL, file path or secrets; request id shown if available. | K213: NOT TESTED | L213: YES | M213: SA-ERR-TC-ERR-005-500.png | Q213: Ask developer for a safe trigger; never break production. | URL: /
A214: TC-ERR-006 | B214: ERR | C214: Livewire/network error | D214: Employee | E214: own | F214: Low | G214: Developer tools open. | H214: 1. Set the browser offline; press Submit on a form. 2. Go back online. | I214: A readable failure message appears; after reconnecting the user can retry without refresh loops. | K214: NOT TESTED | L214: NO | Q214: URL: /time-off/my
A215: TC-E2E-001 | B215: E2E | C215: Employee full journey | D215: Employee | E215: role | F215: Critical | G215: Complete Employee test data prepared; clean browser profile. | H215: 1. Perform the journey in order: Login > Dashboard > Attendance (view today) > Leave balance > Submit leave > Inbox notification > Submit OT > My payslips > My Profile > Documents > Help & Guide > Logout. 2. At each stop capture one screenshot. 3. Note any wait, error, or surprise. | I215: Every stop loads without error; data shown belongs to the role’s scope; notifications arrive at the right recipients; no forbidden page is reachable; user can complete the journey using Help & Guide only. | K215: NOT TESTED | L215: YES | M215: EMP-E2E-TC-E2E-001-journey.png | Q215: URL: /login
A216: TC-E2E-002 | B216: E2E | C216: Manager full journey | D216: Manager | E216: role | F216: Critical | G216: Complete Manager test data prepared; clean browser profile. | H216: 1. Perform the journey in order: Login > Team dashboard > Team attendance > Approve leave > Approve OT > Team performance review > Notifications > Logout. 2. At each stop capture one screenshot. 3. Note any wait, error, or surprise. | I216: Every stop loads without error; data shown belongs to the role’s scope; notifications arrive at the right recipients; no forbidden page is reachable; user can complete the journey using Help & Guide only. | K216: NOT TESTED | L216: YES | M216: MGR-E2E-TC-E2E-002-journey.png | Q216: URL: /login
A217: TC-E2E-003 | B217: E2E | C217: HR Admin full journey | D217: HR Admin | E217: role | F217: Critical | G217: Complete HR Admin test data prepared; clean browser profile. | H217: 1. Perform the journey in order: Login > HR dashboard > Pending regularisations (approve one) > Leave queue > Employees (create + edit) > Onboarding > Documents > Reports > Audit log > Logout. 2. At each stop capture one screenshot. 3. Note any wait, error, or surprise. | I217: Every stop loads without error; data shown belongs to the role’s scope; notifications arrive at the right recipients; no forbidden page is reachable; user can complete the journey using Help & Guide only. | K217: NOT TESTED | L217: YES | M217: HR-E2E-TC-E2E-003-journey.png | Q217: URL: /login
A218: TC-E2E-004 | B218: E2E | C218: Finance full journey | D218: Finance | E218: role | F218: Critical | G218: Complete Finance test data prepared; clean browser profile. | H218: 1. Perform the journey in order: Login > Finance dashboard > Process payroll (draft) > Review OT/incentives/reimbursements > Finance approval > Payslips issued > Payroll reports > Logout. 2. At each stop capture one screenshot. 3. Note any wait, error, or surprise. | I218: Every stop loads without error; data shown belongs to the role’s scope; notifications arrive at the right recipients; no forbidden page is reachable; user can complete the journey using Help & Guide only. | K218: NOT TESTED | L218: YES | M218: FIN-E2E-TC-E2E-004-journey.png | Q218: URL: /login
A219: TC-E2E-005 | B219: E2E | C219: Director / Department Head full journey | D219: Director / Department Head | E219: role | F219: Critical | G219: Complete Director / Department Head test data prepared; clean browser profile. | H219: 1. Perform the journey in order: Login > Department dashboard > Department attendance > Approve department leave > Encashment decision > Department performance > Reports > Try a Marketing URL (expect 403) > Logout. 2. At each stop capture one screenshot. 3. Note any wait, error, or surprise. | I219: Every stop loads without error; data shown belongs to the role’s scope; notifications arrive at the right recipients; no forbidden page is reachable; user can complete the journey using Help & Guide only. | K219: NOT TESTED | L219: YES | M219: DIR-E2E-TC-E2E-005-journey.png | Q219: URL: /login
A220: TC-E2E-006 | B220: E2E | C220: Coordinator full journey | D220: Coordinator | E220: role | F220: Critical | G220: Complete Coordinator test data prepared; clean browser profile. | H220: 1. Perform the journey in order: Login > Dashboard > Attendance Exceptions > Send a reminder > Escalate one issue > Verify only assigned employees appear > Logout. 2. At each stop capture one screenshot. 3. Note any wait, error, or surprise. | I220: Every stop loads without error; data shown belongs to the role’s scope; notifications arrive at the right recipients; no forbidden page is reachable; user can complete the journey using Help & Guide only. | K220: NOT TESTED | L220: YES | M220: COO-E2E-TC-E2E-006-journey.png | Q220: URL: /login
A221: TC-E2E-007 | B221: E2E | C221: Super Admin full journey | D221: Super Admin | E221: role | F221: Critical | G221: Complete Super Admin test data prepared; clean browser profile. | H221: 1. Perform the journey in order: Login > Executive dashboard > Roles & Permissions > Settings (modules, menu) > Payroll approval policy > Audit log > Data management (view only) > Logout. 2. At each stop capture one screenshot. 3. Note any wait, error, or surprise. | I221: Every stop loads without error; data shown belongs to the role’s scope; notifications arrive at the right recipients; no forbidden page is reachable; user can complete the journey using Help & Guide only. | K221: NOT TESTED | L221: YES | M221: SA-E2E-TC-E2E-007-journey.png | Q221: URL: /login
A222: TC-SEC-001 | B222: SEC | C222: Negative access sweep | D222: Employee | E222: role | F222: Critical | G222: Signed in as Employee; ids of a record outside scope noted. | H222: 1. Change the employee id in /employees/{id}/profile to one outside scope. 2. Open another employee’s payslip download URL. 3. Open an HR-only URL (/settings/roles) and a Finance-only URL (/payroll/process) not allowed for the role. 4. Open a disabled module route. 5. Copy a signed document URL into a different user’s browser. | I222: Every attempt returns 403/404/invalid signature. No other person’s sensitive data appears in the page, title, error text or downloaded file. | K222: NOT TESTED | L222: YES | M222: EMP-SEC-TC-SEC-001-negative-sweep.png | Q222: URL: /
A223: TC-SEC-002 | B223: SEC | C223: Negative access sweep | D223: Manager | E223: role | F223: Critical | G223: Signed in as Manager; ids of a record outside scope noted. | H223: 1. Change the employee id in /employees/{id}/profile to one outside scope. 2. Open another employee’s payslip download URL. 3. Open an HR-only URL (/settings/roles) and a Finance-only URL (/payroll/process) not allowed for the role. 4. Open a disabled module route. 5. Copy a signed document URL into a different user’s browser. | I223: Every attempt returns 403/404/invalid signature. No other person’s sensitive data appears in the page, title, error text or downloaded file. | K223: NOT TESTED | L223: YES | M223: MGR-SEC-TC-SEC-002-negative-sweep.png | Q223: URL: /
A224: TC-SEC-003 | B224: SEC | C224: Negative access sweep | D224: Director / Department Head | E224: role | F224: Critical | G224: Signed in as Director / Department Head; ids of a record outside scope noted. | H224: 1. Change the employee id in /employees/{id}/profile to one outside scope. 2. Open another employee’s payslip download URL. 3. Open an HR-only URL (/settings/roles) and a Finance-only URL (/payroll/process) not allowed for the role. 4. Open a disabled module route. 5. Copy a signed document URL into a different user’s browser. | I224: Every attempt returns 403/404/invalid signature. No other person’s sensitive data appears in the page, title, error text or downloaded file. | K224: NOT TESTED | L224: YES | M224: DIR-SEC-TC-SEC-003-negative-sweep.png | Q224: URL: /
A225: TC-SEC-004 | B225: SEC | C225: Negative access sweep | D225: Finance | E225: role | F225: Critical | G225: Signed in as Finance; ids of a record outside scope noted. | H225: 1. Change the employee id in /employees/{id}/profile to one outside scope. 2. Open another employee’s payslip download URL. 3. Open an HR-only URL (/settings/roles) and a Finance-only URL (/payroll/process) not allowed for the role. 4. Open a disabled module route. 5. Copy a signed document URL into a different user’s browser. | I225: Every attempt returns 403/404/invalid signature. No other person’s sensitive data appears in the page, title, error text or downloaded file. | K225: NOT TESTED | L225: YES | M225: FIN-SEC-TC-SEC-004-negative-sweep.png | Q225: URL: /
A226: TC-SEC-005 | B226: SEC | C226: Negative access sweep | D226: Coordinator | E226: role | F226: Critical | G226: Signed in as Coordinator; ids of a record outside scope noted. | H226: 1. Change the employee id in /employees/{id}/profile to one outside scope. 2. Open another employee’s payslip download URL. 3. Open an HR-only URL (/settings/roles) and a Finance-only URL (/payroll/process) not allowed for the role. 4. Open a disabled module route. 5. Copy a signed document URL into a different user’s browser. | I226: Every attempt returns 403/404/invalid signature. No other person’s sensitive data appears in the page, title, error text or downloaded file. | K226: NOT TESTED | L226: YES | M226: COO-SEC-TC-SEC-005-negative-sweep.png | Q226: URL: /
... A231: TC-AUDIT-002 | B231: AUDIT | C231: Audit visibility | D231: Finance | E231: finance | F231: Medium | G231: Finance. | H231: 1. Open the audit log; open /payroll/audit-trail. | I231: Finance sees only payroll audit if allowed; general audit log limited to SA/HR (gap AUD-08). | K231: NOT TESTED | L231: YES | M231: FIN-AUDIT-TC-AUDIT-002-visibility.png | Q231: AUD-08 | URL: /settings/audit-log

Sheet Summary
A1: Metric | B1: Count
A2: Total Test Cases | B2: =COUNTA(Cases!A2:A231)
A3: Passed | B3: =COUNTIF(Cases!K2:K231,"PASS")
A4: Failed | B4: =COUNTIF(Cases!K2:K231,"FAIL")
A5: Blocked | B5: =COUNTIF(Cases!K2:K231,"BLOCKED")
A6: Not Tested | B6: =COUNTIF(Cases!K2:K231,"NOT TESTED")
A8: By Role (cases) | B8: Count
A9: Super Admin | B9: =COUNTIF(Cases!D2:D231,A9)
A10: HR Admin | B10: =COUNTIF(Cases!D2:D231,A10)
A11: Director / Department Head | B11: =COUNTIF(Cases!D2:D231,A11)
A12: Manager | B12: =COUNTIF(Cases!D2:D231,A12)
A13: Finance | B13: =COUNTIF(Cases!D2:D231,A13)
A14: Coordinator | B14: =COUNTIF(Cases!D2:D231,A14)
A15: Employee | B15: =COUNTIF(Cases!D2:D231,A15)
A17: By Module (cases) | B17: Count
A18: ARREARS | B18: =COUNTIF(Cases!B2:B231,A18)
A19: ATT | B19: =COUNTIF(Cases!B2:B231,A19)
A20: AUDIT | B20: =COUNTIF(Cases!B2:B231,A20)
A21: AUTH | B21: =COUNTIF(Cases!B2:B231,A21)
A22: CYCLE | B22: =COUNTIF(Cases!B2:B231,A22)
A23: DASH | B23: =COUNTIF(Cases!B2:B231,A23)
A24: E2E | B24: =COUNTIF(Cases!B2:B231,A24)
A25: EMPMGT | B25: =COUNTIF(Cases!B2:B231,A25)
A26: ENCASH | B26: =COUNTIF(Cases!B2:B231,A26)
A27: ERR | B27: =COUNTIF(Cases!B2:B231,A27)
A28: HELP | B28: =COUNTIF(Cases!B2:B231,A28)
A29: JOBS | B29: =COUNTIF(Cases!B2:B231,A29)
A30: LEAVE | B30: =COUNTIF(Cases!B2:B231,A30)
A31: NOTIF | B31: =COUNTIF(Cases!B2:B231,A31)
A32: ONOFF | B32: =COUNTIF(Cases!B2:B231,A32)
A33: OT | B33: =COUNTIF(Cases!B2:B231,A33)
A34: PAY | B34: =COUNTIF(Cases!B2:B231,A34)
A35: PERF | B35: =COUNTIF(Cases!B2:B231,A35)
A36: RBAC | B36: =COUNTIF(Cases!B2:B231,A36)
A37: REG | B37: =COUNTIF(Cases!B2:B231,A37)
A38: SEC | B38: =COUNTIF(Cases!B2:B231,A38)
A39: UI | B39: =COUNTIF(Cases!B2:B231,A39)
